mathmat/__init__.py
mathmat/factor.py
mathmat/mathmat.py
mathmat/random.py
mathmat/solve.py
mathmat/vis.py
mathmat-1.0.0.dist-info/METADATA
mathmat-1.0.0.dist-info/WHEEL
mathmat-1.0.0.dist-info/licenses/LICENSE
mathmat-1.0.0.dist-info/RECORD
